{
  "$schema": "https://developer.microsoft.com/json-schemas/fabric/item/report/definition/visualContainer/2.10.0/schema.json",
  "name": "e141b1b486948ba17423",
  "position": {
    "x": 30,
    "y": 98,
    "z": 3,
    "height": 135,
    "width": 1220,
    "tabOrder": 3
  },
  "visual": {
    "visualType": "cardVisual",
    "query": {
      "queryState": {
        "Data": {
          "projections": [
            {
              "field": {
                "Measure": {
                  "Expression": {
                    "SourceRef": {
                      "Entity": "_Measures"
                    }
                  },
                  "Property": "Total Earthquakes"
                }
              },
              "queryRef": "_Measures.Total Earthquakes",
              "nativeQueryRef": "Total Earthquakes"
            },
            {
              "field": {
                "Measure": {
                  "Expression": {
                    "SourceRef": {
                      "Entity": "_Measures"
                    }
                  },
                  "Property": "Avg Magnitude"
                }
              },
              "queryRef": "_Measures.Avg Magnitude",
              "nativeQueryRef": "Avg Magnitude"
            },
            {
              "field": {
                "Measure": {
                  "Expression": {
                    "SourceRef": {
                      "Entity": "_Measures"
                    }
                  },
                  "Property": "Max Magnitude"
                }
              },
              "queryRef": "_Measures.Max Magnitude",
              "nativeQueryRef": "Max Magnitude"
            },
            {
              "field": {
                "Measure": {
                  "Expression": {
                    "SourceRef": {
                      "Entity": "_Measures"
                    }
                  },
                  "Property": "Max Significance"
                }
              },
              "queryRef": "_Measures.Max Significance",
              "nativeQueryRef": "Max Significance"
            },
            {
              "field": {
                "Measure": {
                  "Expression": {
                    "SourceRef": {
                      "Entity": "_Measures"
                    }
                  },
                  "Property": "% High Significance"
                }
              },
              "queryRef": "_Measures.% High Significance",
              "nativeQueryRef": "% High Significance"
            }
          ]
        }
      },
      "sortDefinition": {
        "sort": [
          {
            "field": {
              "Measure": {
                "Expression": {
                  "SourceRef": {
                    "Entity": "_Measures"
                  }
                },
                "Property": "Total Earthquakes"
              }
            },
            "direction": "Descending"
          }
        ],
        "isDefaultSort": true
      }
    },
    "objects": {
      "label": [
        {
          "properties": {
            "position": {
              "expr": {
                "Literal": {
                  "Value": "'aboveValue'"
                }
              }
            }
          },
          "selector": {
            "id": "default"
          }
        },
        {
          "properties": {
            "text": {
              "expr": {
                "Literal": {
                  "Value": "'Total Events'"
                }
              }
            }
          },
          "selector": {
            "metadata": "_Measures.Total Earthquakes"
          }
        },
        {
          "properties": {
            "text": {
              "expr": {
                "Literal": {
                  "Value": "'Highest Magnitude'"
                }
              }
            }
          },
          "selector": {
            "metadata": "_Measures.Max Magnitude"
          }
        },
        {
          "properties": {
            "text": {
              "expr": {
                "Literal": {
                  "Value": "'Peak Significance'"
                }
              }
            }
          },
          "selector": {
            "metadata": "_Measures.Max Significance"
          }
        },
        {
          "properties": {
            "text": {
              "expr": {
                "Literal": {
                  "Value": "'High Significance %'"
                }
              }
            }
          },
          "selector": {
            "metadata": "_Measures.% High Significance"
          }
        }
      ],
      "value": [
        {
          "properties": {
            "horizontalAlignment": {
              "expr": {
                "Literal": {
                  "Value": "'center'"
                }
              }
            }
          },
          "selector": {
            "metadata": "_Measures.% High Significance"
          }
        },
        {
          "properties": {
            "horizontalAlignment": {
              "expr": {
                "Literal": {
                  "Value": "'center'"
                }
              }
            }
          },
          "selector": {
            "id": "default"
          }
        }
      ]
    },
    "visualContainerObjects": {
      "dropShadow": [
        {
          "properties": {
            "show": {
              "expr": {
                "Literal": {
                  "Value": "true"
                }
              }
            }
          }
        }
      ]
    },
    "drillFilterOtherVisuals": true
  },
  "filterConfig": {
    "filters": [
      {
        "name": "ab22ce4ae9b13dc0a011",
        "field": {
          "Measure": {
            "Expression": {
              "SourceRef": {
                "Entity": "_Measures"
              }
            },
            "Property": "Total Earthquakes"
          }
        },
        "type": "Advanced"
      },
      {
        "name": "e4c42e03b9ad6774b8da",
        "field": {
          "Measure": {
            "Expression": {
              "SourceRef": {
                "Entity": "_Measures"
              }
            },
            "Property": "Avg Magnitude"
          }
        },
        "type": "Advanced"
      },
      {
        "name": "c20ade6da6307443491b",
        "field": {
          "Measure": {
            "Expression": {
              "SourceRef": {
                "Entity": "_Measures"
              }
            },
            "Property": "Max Magnitude"
          }
        },
        "type": "Advanced"
      },
      {
        "name": "75e8764b354aa8a85128",
        "field": {
          "Measure": {
            "Expression": {
              "SourceRef": {
                "Entity": "_Measures"
              }
            },
            "Property": "Max Significance"
          }
        },
        "type": "Advanced"
      },
      {
        "name": "f7f01c29f74a6e7b5fce",
        "field": {
          "Measure": {
            "Expression": {
              "SourceRef": {
                "Entity": "_Measures"
              }
            },
            "Property": "% High Significance"
          }
        },
        "type": "Advanced"
      }
    ]
  }
}